google_datacatalog_sqlserver_connector-0.10.0-py3.8-nspkg.pth
google/datacatalog_connectors/sqlserver/__init__.py
google/datacatalog_connectors/sqlserver/datacatalog_cli.py
google/datacatalog_connectors/sqlserver/config/__init__.py
google/datacatalog_connectors/sqlserver/config/metadata_definition.json
google/datacatalog_connectors/sqlserver/config/metadata_definition_functions_sql_object.json
google/datacatalog_connectors/sqlserver/config/metadata_definition_stored_procedures_sql_object.json
google/datacatalog_connectors/sqlserver/config/metadata_definition_triggers_sql_object.json
google/datacatalog_connectors/sqlserver/config/metadata_query.sql
google/datacatalog_connectors/sqlserver/config/query_functions_sql_object.sql
google/datacatalog_connectors/sqlserver/config/query_stored_procedures_sql_object.sql
google/datacatalog_connectors/sqlserver/config/query_triggers_sql_object.sql
google/datacatalog_connectors/sqlserver/scrape/__init__.py
google/datacatalog_connectors/sqlserver/scrape/metadata_scraper.py
google_datacatalog_sqlserver_connector-0.10.0.dist-info/METADATA
google_datacatalog_sqlserver_connector-0.10.0.dist-info/WHEEL
google_datacatalog_sqlserver_connector-0.10.0.dist-info/entry_points.txt
google_datacatalog_sqlserver_connector-0.10.0.dist-info/namespace_packages.txt
google_datacatalog_sqlserver_connector-0.10.0.dist-info/top_level.txt
google_datacatalog_sqlserver_connector-0.10.0.dist-info/RECORD
