Metadata-Version: 2.1
Name: google-datacatalog-sqlserver-connector
Version: 0.10.0
Summary: Library for ingesting SQLServer metadata into Google Cloud Data Catalog
Home-page: UNKNOWN
Author: Google LLC
License: UNKNOWN
Platform: Posix; MacOS X; Windows
Classifier: Development Status :: 4 - Beta
Classifier: Programming Language :: Python :: 3.7
Requires-Dist: pyodbc
Requires-Dist: google-datacatalog-rdbms-connector (>=0.12.0<0.13.0)
